pyspark_bucketmap.py
pyspark_bucketmap-0.0.5.data/scripts/pyspark_bucketmap.py
pyspark_bucketmap-0.0.5.dist-info/LICENSE
pyspark_bucketmap-0.0.5.dist-info/METADATA
pyspark_bucketmap-0.0.5.dist-info/WHEEL
pyspark_bucketmap-0.0.5.dist-info/top_level.txt
pyspark_bucketmap-0.0.5.dist-info/RECORD
