Metadata-Version: 2.1
Name: pyspark-bucketmap
Version: 0.0.5
Summary: Easily group pyspark data into buckets and map them to different values.
Home-page: https://github.com/dunnkers/pyspark-bucketmap
Author: Jeroen Overschie
Author-email: jeroen@darius.nl
Maintainer: Jeroen Overschie
Maintainer-email: jeroen@darius.nl
License: MIT
Project-URL: Github, https://github.com/dunnkers/pyspark-bucketmap
Project-URL: Bug Tracker, https://github.com/dunnkers/pyspark-bucketmap/issues
Project-URL: Documentation, https://dunnkers.com/pyspark-bucketmap
Classifier: License :: OSI Approved :: MIT License
Classifier: Development Status :: 4 - Beta
Classifier: Programming Language :: Python :: 3.7
Classifier: Programming Language :: Python :: 3.8
Classifier: Programming Language :: Python :: 3.9
Classifier: Operating System :: POSIX :: Linux
Classifier: Operating System :: MacOS
Classifier: Operating System :: Microsoft :: Windows
Classifier: Typing :: Typed
Classifier: Topic :: Scientific/Engineering
Classifier: Topic :: Software Development
Classifier: Topic :: Software Development :: Libraries :: Python Modules
Requires-Python: >= 3.7
License-File: LICENSE
Requires-Dist: pyspark (>=1.4.0)
Requires-Dist: overrides (>=4.0.0)
Requires-Dist: numpy (>=1.19.0)
